varphitape/__init__.py
varphitape/antlr/VarphiTapeEvaluator.py
varphitape/antlr/VarphiTapeLexer.py
varphitape/antlr/VarphiTapeListener.py
varphitape/antlr/VarphiTapeParser.py
varphitape/antlr/__init__.py
varphitape/frontend/__init__.py
varphitape/frontend/frontend.py
varphitape/model/Tape.py
varphitape/model/__init__.py
varphitape-1.0.dist-info/LICENSE
varphitape-1.0.dist-info/METADATA
varphitape-1.0.dist-info/WHEEL
varphitape-1.0.dist-info/top_level.txt
varphitape-1.0.dist-info/RECORD
